{"ReportText": "CLINICAL DATA: Chest pain. EXAM: CHEST 2 VIEW COMPARISON: None. FINDINGS: Normal heart size and mediastinal contours. No acute infiltrate or edema. No effusion or pneumothorax. No acute osseous findings. IMPRESSION: No active cardiopulmonary disease. Electronically Signed By: [[PERSONALNAME] On: 08/07/2015 17:38", "findings": "FINDINGS: Normal heart size and mediastinal contours. No acute infiltrate or edema. No effusion or pneumothorax. No acute osseous findings. \n\n", "clinicaldata": "CLINICAL DATA: Chest pain. \n\n", "ExamName": "EXAM: CHEST 2 VIEW\n\nCOMPARISON: None.", "impression": "IMPRESSION: No active cardiopulmonary disease. Electronically Signed By: [[PERSONALNAME] On: 08/07/2015 17:38"}