{"ReportText": "EXAM: XR CHEST 1 VIEW DATE: 05/03/2017 2:27 PM HISTORY: chest pain TECHNIQUE: AP chest COMPARISON: None available FINDINGS: No confluent infiltrates or effusions; lungs well expanded. Cardiomediastinal silhouette within normal limits. Osseous structures unremarkable for acute findings. IMPRESSION: No acute cardiopulmonary process. [PERSONALNAME] ELECTRONICALLY SIGNED BY:[PERSONALNAME]", "findings": "FINDINGS: No confluent infiltrates or effusions; lungs well expanded. Cardiomediastinal silhouette within normal limits. Osseous structures unremarkable for acute findings. \n\n", "clinicaldata": "HISTORY: chest pain \n\n", "ExamName": "EXAM: XR CHEST 1 VIEW DATE: 05/03/2017 2:27 PM\n\nTECHNIQUE: AP chest\n\nCOMPARISON: None available", "impression": "IMPRESSION: No acute cardiopulmonary process. [PERSONALNAME] ELECTRONICALLY SIGNED BY:[PERSONALNAME]"}