{"ReportText": "Exam: CHEST AP (1 VIEW) History: SP OH SURGERY Comparison: Yesterday Findings: [ID] hours Endotracheal tube and NG tube have been removed in the interim. Swan-Ganz catheter and thoracostomy tubes remain in place. Heart size is stable. Atelectatic changes persist within the left lung base. No pneumothorax. Bony structures are unchanged. Impression: As above. Electronically Signed by: [[PERSONALNAME], MD", "findings": "Findings: [ID] hours Endotracheal tube and NG tube have been removed in the interim. Swan-Ganz catheter and thoracostomy tubes remain in place. Heart size is stable. Atelectatic changes persist within the left lung base. No pneumothorax. Bony structures are unchanged. \n\n", "clinicaldata": "History: SP OH SURGERY \n\n", "ExamName": "Exam: CHEST AP (1 VIEW)\n\nComparison: Yesterday", "impression": "Impression: As above. Electronically Signed by: [[PERSONALNAME], MD"}